LICENSE.txt
MANIFEST.in
README.md
requirements.txt
setup.cfg
setup.py
prototwin/__init__.py
prototwin/client.py
prototwin.egg-info/PKG-INFO
prototwin.egg-info/SOURCES.txt
prototwin.egg-info/dependency_links.txt
prototwin.egg-info/requires.txt
prototwin.egg-info/top_level.txt