Metadata-Version: 2.1
Name: prototwin
Version: 0.1.15
Summary: The official python client interface for ProtoTwin Connect.
Home-page: https://prototwin.com
Author: ProtoTwin
License: MIT
Keywords: Industrial Simulation,Physics,Machine Learning,Robotics
Classifier: Development Status :: 4 - Beta
Classifier: Intended Audience :: Developers
Classifier: Topic :: Scientific/Engineering :: Artificial Intelligence
Classifier: License :: OSI Approved :: MIT License
Classifier: Programming Language :: Python :: 3
License-File: LICENSE.txt
Requires-Dist: asyncio
Requires-Dist: websockets
Requires-Dist: prototwin_cmdbuff
